cerc_persistence/__init__.py
cerc_persistence/configuration.py
cerc_persistence/db_control.py
cerc_persistence/db_setup.py
cerc_persistence/repository.py
cerc_persistence/version.py
cerc_persistence/models/__init__.py
cerc_persistence/models/application.py
cerc_persistence/models/city.py
cerc_persistence/models/city_object.py
cerc_persistence/models/simulation_results.py
cerc_persistence/models/user.py
cerc_persistence/repositories/__init__.py
cerc_persistence/repositories/application.py
cerc_persistence/repositories/city.py
cerc_persistence/repositories/city_object.py
cerc_persistence/repositories/simulation_results.py
cerc_persistence/repositories/user.py
cerc_persistence/types/__init__.py
cerc_persistence/types/float_or_npfloat.py
cerc_persistence-1.0.0.5.data/data/cerc_persistence/requirements.txt
cerc_persistence-1.0.0.5.dist-info/METADATA
cerc_persistence-1.0.0.5.dist-info/WHEEL
cerc_persistence-1.0.0.5.dist-info/top_level.txt
cerc_persistence-1.0.0.5.dist-info/RECORD
