Metadata-Version: 2.4
Name: cerc-persistence
Version: 1.0.0.5
Summary: CERC Persistence consist of a set of classes to store and retrieve Cerc Hub cities and results
Classifier: License :: OSI Approved :: GNU Library or Lesser General Public License (LGPL)
Classifier: Programming Language :: Python
Classifier: Programming Language :: Python :: 3
Requires-Dist: python-dotenv
Requires-Dist: SQLAlchemy
Requires-Dist: cerc-hub
Requires-Dist: psycopg2-binary
Requires-Dist: sqlalchemy_utils
Requires-Dist: setuptools
Dynamic: classifier
Dynamic: description
Dynamic: requires-dist
Dynamic: summary
